setup.py
digitizer/__init__.py
digitizer/parser.py
digitizer.egg-info/PKG-INFO
digitizer.egg-info/SOURCES.txt
digitizer.egg-info/dependency_links.txt
digitizer.egg-info/requires.txt
digitizer.egg-info/top_level.txt