Metadata-Version: 2.1
Name: digitizer
Version: 0.1.2
Summary: Paser for the caen DT5742
Home-page: https://github.com/Tsangares/
Author: William Wyatt
Author-email: wwyatt@ucsc.edu
License: UNKNOWN
Platform: UNKNOWN
Classifier: Programming Language :: Python :: 3
Classifier: License :: OSI Approved :: MIT License
